lemonshark/__init__.py
lemonshark/buffer.py
lemonshark/encoding.py
lemonshark/epan_field.py
lemonshark/epan_packet.py
lemonshark/field.py
lemonshark/field_description.py
lemonshark/field_type.py
lemonshark/filter.py
lemonshark/lemonshark.py
lemonshark/packet.py
lemonshark/session.py
lemonshark/native/linux/x86_64/liblemonshark.so
lemonshark/native/windows/amd64/liblemonshark.dll
lemonshark/native/windows/amd64/liblemonshark.lib
lemonshark/native/windows/amd64/liblemonshark.pdb
lemonshark-0.10.0.dist-info/licenses/LICENSE
lemonshark-0.10.0.dist-info/METADATA
lemonshark-0.10.0.dist-info/WHEEL
lemonshark-0.10.0.dist-info/top_level.txt
lemonshark-0.10.0.dist-info/RECORD
