Metadata-Version: 2.4
Name: lemonshark
Version: 0.10.0
Summary: lemonshark allows to use Wireshark as a library in an python application
Home-page: https://github.com/CodeDevAM/lemonshark
Author: DevAM
Author-email: email@example.com
License: GPL-2.0-only
Keywords: lemonshark,shark,Wireshark
License-File: LICENSE
Dynamic: author
Dynamic: author-email
Dynamic: description
Dynamic: description-content-type
Dynamic: home-page
Dynamic: keywords
Dynamic: license
Dynamic: license-file
Dynamic: summary
